itrs-0.1.1.dist-info/METADATA
itrs-0.1.1.dist-info/WHEEL
itrs.cpython-38-x86_64-linux-gnu.so
itrs-0.1.1.dist-info/RECORD
