Metadata-Version: 2.1
Name: itrs
Version: 0.1.1
Summary: Itrs is a python native module that exposes to python an Iterator interface similar to Rust's Iterator trait. Implemented in Rust.
Author: Louis Dureuil <louis.dureuil@xinra.net>
Author-Email: Louis Dureuil <louis.dureuil@xinra.net>
